getcohorts/__init__.py
getcohorts/core.py
getcohorts/web.py
getcohorts-1.0.0.dist-info/LICENSE
getcohorts-1.0.0.dist-info/METADATA
getcohorts-1.0.0.dist-info/WHEEL
getcohorts-1.0.0.dist-info/top_level.txt
getcohorts-1.0.0.dist-info/RECORD
