Metadata-Version: 2.1
Name: getcohorts
Version: 1.0.0
Summary: Utilities for randomizing A/B tests
Home-page: http://docs.getcohorts.com/
Author: Tom Waterman
Author-email: tjwaterman99@gmail.com
License: UNKNOWN
Platform: UNKNOWN
Classifier: Programming Language :: Python :: 3
Classifier: License :: OSI Approved :: MIT License
Classifier: Operating System :: OS Independent
Requires-Python: >=3.6
Requires-Dist: gunicorn (==20.0.4)
Requires-Dist: fastapi (==0.61.1)
Requires-Dist: uvicorn (==0.11.8)
